aioxlsxstream/__init__.py
aioxlsxstream/aioxlsxstream.py
aioxlsxstream/xlsx_template/[Content_Types].xml
aioxlsxstream/xlsx_template/_rels/.rels
aioxlsxstream/xlsx_template/docProps/app.xml
aioxlsxstream/xlsx_template/docProps/core.xml
aioxlsxstream/xlsx_template/xl/styles.xml
aioxlsxstream/xlsx_template/xl/workbook.xml
aioxlsxstream/xlsx_template/xl/_rels/workbook.xml.rels
aioxlsxstream/xlsx_template/xl/theme/theme1.xml
aioxlsxstream-1.0.3.dist-info/LICENSE
aioxlsxstream-1.0.3.dist-info/METADATA
aioxlsxstream-1.0.3.dist-info/WHEEL
aioxlsxstream-1.0.3.dist-info/top_level.txt
aioxlsxstream-1.0.3.dist-info/RECORD
