Metadata-Version: 2.1
Name: aioxlsxstream
Version: 1.0.3
Summary: Asynchronous xlsx files generator
Home-page: https://github.com/lososkin/aioxlsxstream
Author: lososkin
Author-email: yalososka@gmail.com
License: UNKNOWN
Keywords: async xlsx streaming
Platform: UNKNOWN
Classifier: Programming Language :: Python
Classifier: License :: OSI Approved :: GNU General Public License v3 (GPLv3)
Classifier: Operating System :: OS Independent
Classifier: Topic :: System :: Archiving :: Compression
License-File: LICENSE
Requires-Dist: asynczipstream (>=1.0.1)
